disparity_view/__init__.py
disparity_view/animation_gif.py
disparity_view/cam_param.py
disparity_view/depth_to_normal.py
disparity_view/o3d_project.py
disparity_view/util.py
disparity_view/view.py
disparity_view/zed_capture.py
disparity_view-0.1.0.dist-info/LICENSE
disparity_view-0.1.0.dist-info/METADATA
disparity_view-0.1.0.dist-info/WHEEL
disparity_view-0.1.0.dist-info/entry_points.txt
disparity_view-0.1.0.dist-info/top_level.txt
disparity_view-0.1.0.dist-info/RECORD
