Metadata-Version: 2.1
Name: disparity_view
Version: 0.1.0
Summary: disparity npy file viewer
Author-email: katsunori-waragai <huyuhiko1128@gmail.com>, zhang chao <zhang.chao@borgroid.co.jp>
Project-URL: Repository, https://github.com/katsunori-waragai/disparity-view
Requires-Python: >=3.8
License-File: LICENSE
Requires-Dist: dataclasses-json
Requires-Dist: numpy <2
Requires-Dist: opencv-python >=3.4.18.65
Requires-Dist: open3d >=0.16.0
Requires-Dist: pillow >=10.1.0
Requires-Dist: scikit-image
Requires-Dist: tqdm
Requires-Dist: typing-extensions >=4.7.1
Provides-Extra: dev
Requires-Dist: pytest ; extra == 'dev'
Requires-Dist: black ; extra == 'dev'
